Workbook

Sheet Assumptions
A1: Salary Calculator - Assumptions
A2: Yellow cells are editable inputs. All calculations update automatically.
A4: HRA (% of Basic) | B4: 0.4
A5: Special Allowance (% of Basic) | B5: 0.2
A6: Employee PF (% of Basic) | B6: 0.12
A7: Professional Tax (monthly, flat) | B7: 200
A8: Performance Bonus (% of Basic, if eligible) | B8: 0.1
A9: Income Tax Slab 1 (up to this annual gross, taxed at Rate 1) | B9: 500000
A10: Tax Rate 1 | B10: 0.05
A11: Tax Rate 2 (above Slab 1) | B11: 0.15

Sheet Salary Calculator
A1: Monthly Salary Calculator
A2: Enter Employee Name, Department, Basic Salary, and Bonus Eligible (Yes/No) — everything else calculates automatically.
A4: Emp ID | B4: Name | C4: Department | D4: Basic Salary | E4: HRA | F4: Special Allowance | G4: Bonus Eligible | H4: Bonus | I4: Gross Salary | J4: Employee PF | K4: Professional Tax | L4: Income Tax | M4: Total Deductions | N4: Net Salary
A5: E001 | B5: Aarav Sharma | C5: Sales | D5: 55000 | E5: =D5*Assumptions!$B$4 -> 22000 | F5: =D5*Assumptions!$B$5 -> 11000 | G5: Yes | H5: =IF(G5="Yes",D5*Assumptions!$B$8,0) -> 5500 | I5: =D5+E5+F5+H5 -> 93500 | J5: =D5*Assumptions!$B$6 -> 6600 | K5: =Assumptions!$B$7 -> 200 | L5: =IF(I5*12<=Assumptions!$B$9,I5*Assumptions!$B$10,I5*Assumptions!$B$11) -> 14025 | M5: =J5+K5+L5 -> 20825 | N5: =I5-M5 -> 72675
A6: E002 | B6: Priya Nair | C6: Sales | D6: 65000 | E6: =D6*Assumptions!$B$4 -> 26000 | F6: =D6*Assumptions!$B$5 -> 13000 | G6: No | H6: =IF(G6="Yes",D6*Assumptions!$B$8,0) -> 0 | I6: =D6+E6+F6+H6 -> 104000 | J6: =D6*Assumptions!$B$6 -> 7800 | K6: =Assumptions!$B$7 -> 200 | L6: =IF(I6*12<=Assumptions!$B$9,I6*Assumptions!$B$10,I6*Assumptions!$B$11) -> 15600 | M6: =J6+K6+L6 -> 23600 | N6: =I6-M6 -> 80400
A7: E003 | B7: Rohan Mehta | C7: IT | D7: 25000 | E7: =D7*Assumptions!$B$4 -> 10000 | F7: =D7*Assumptions!$B$5 -> 5000 | G7: Yes | H7: =IF(G7="Yes",D7*Assumptions!$B$8,0) -> 2500 | I7: =D7+E7+F7+H7 -> 42500 | J7: =D7*Assumptions!$B$6 -> 3000 | K7: =Assumptions!$B$7 -> 200 | L7: =IF(I7*12<=Assumptions!$B$9,I7*Assumptions!$B$10,I7*Assumptions!$B$11) -> 6375 | M7: =J7+K7+L7 -> 9575 | N7: =I7-M7 -> 32925
A8: E004 | B8: Sneha Kapoor | C8: IT | D8: 30000 | E8: =D8*Assumptions!$B$4 -> 12000 | F8: =D8*Assumptions!$B$5 -> 6000 | G8: Yes | H8: =IF(G8="Yes",D8*Assumptions!$B$8,0) -> 3000 | I8: =D8+E8+F8+H8 -> 51000 | J8: =D8*Assumptions!$B$6 -> 3600 | K8: =Assumptions!$B$7 -> 200 | L8: =IF(I8*12<=Assumptions!$B$9,I8*Assumptions!$B$10,I8*Assumptions!$B$11) -> 7650 | M8: =J8+K8+L8 -> 11450 | N8: =I8-M8 -> 39550
A9: E005 | B9: Vikram Singh | C9: HR | D9: 25000 | E9: =D9*Assumptions!$B$4 -> 10000 | F9: =D9*Assumptions!$B$5 -> 5000 | G9: No | H9: =IF(G9="Yes",D9*Assumptions!$B$8,0) -> 0 | I9: =D9+E9+F9+H9 -> 40000 | J9: =D9*Assumptions!$B$6 -> 3000 | K9: =Assumptions!$B$7 -> 200 | L9: =IF(I9*12<=Assumptions!$B$9,I9*Assumptions!$B$10,I9*Assumptions!$B$11) -> 2000 | M9: =J9+K9+L9 -> 5200 | N9: =I9-M9 -> 34800
A10: E006 | B10: Anjali Rao | C10: HR | D10: 40000 | E10: =D10*Assumptions!$B$4 -> 16000 | F10: =D10*Assumptions!$B$5 -> 8000 | G10: Yes | H10: =IF(G10="Yes",D10*Assumptions!$B$8,0) -> 4000 | I10: =D10+E10+F10+H10 -> 68000 | J10: =D10*Assumptions!$B$6 -> 4800 | K10: =Assumptions!$B$7 -> 200 | L10: =IF(I10*12<=Assumptions!$B$9,I10*Assumptions!$B$10,I10*Assumptions!$B$11) -> 10200 | M10: =J10+K10+L10 -> 15200 | N10: =I10-M10 -> 52800
A11: E007 | B11: Karan Malhotra | C11: Finance | D11: 30000 | E11: =D11*Assumptions!$B$4 -> 12000 | F11: =D11*Assumptions!$B$5 -> 6000 | G11: Yes | H11: =IF(G11="Yes",D11*Assumptions!$B$8,0) -> 3000 | I11: =D11+E11+F11+H11 -> 51000 | J11: =D11*Assumptions!$B$6 -> 3600 | K11: =Assumptions!$B$7 -> 200 | L11: =IF(I11*12<=Assumptions!$B$9,I11*Assumptions!$B$10,I11*Assumptions!$B$11) -> 7650 | M11: =J11+K11+L11 -> 11450 | N11: =I11-M11 -> 39550
A12: E008 | B12: Divya Iyer | C12: Finance | D12: 65000 | E12: =D12*Assumptions!$B$4 -> 26000 | F12: =D12*Assumptions!$B$5 -> 13000 | G12: Yes | H12: =IF(G12="Yes",D12*Assumptions!$B$8,0) -> 6500 | I12: =D12+E12+F12+H12 -> 110500 | J12: =D12*Assumptions!$B$6 -> 7800 | K12: =Assumptions!$B$7 -> 200 | L12: =IF(I12*12<=Assumptions!$B$9,I12*Assumptions!$B$10,I12*Assumptions!$B$11) -> 16575 | M12: =J12+K12+L12 -> 24575 | N12: =I12-M12 -> 85925
A13: E009 | B13: Arjun Verma | C13: IT | D13: 40000 | E13: =D13*Assumptions!$B$4 -> 16000 | F13: =D13*Assumptions!$B$5 -> 8000 | G13: Yes | H13: =IF(G13="Yes",D13*Assumptions!$B$8,0) -> 4000 | I13: =D13+E13+F13+H13 -> 68000 | J13: =D13*Assumptions!$B$6 -> 4800 | K13: =Assumptions!$B$7 -> 200 | L13: =IF(I13*12<=Assumptions!$B$9,I13*Assumptions!$B$10,I13*Assumptions!$B$11) -> 10200 | M13: =J13+K13+L13 -> 15200 | N13: =I13-M13 -> 52800
A14: E010 | B14: Neha Joshi | C14: Sales | D14: 65000 | E14: =D14*Assumptions!$B$4 -> 26000 | F14: =D14*Assumptions!$B$5 -> 13000 | G14: Yes | H14: =IF(G14="Yes",D14*Assumptions!$B$8,0) -> 6500 | I14: =D14+E14+F14+H14 -> 110500 | J14: =D14*Assumptions!$B$6 -> 7800 | K14: =Assumptions!$B$7 -> 200 | L14: =IF(I14*12<=Assumptions!$B$9,I14*Assumptions!$B$10,I14*Assumptions!$B$11) -> 16575 | M14: =J14+K14+L14 -> 24575 | N14: =I14-M14 -> 85925
A15: E011 | B15: Ishaan Bose | C15: Marketing | D15: 30000 | E15: =D15*Assumptions!$B$4 -> 12000 | F15: =D15*Assumptions!$B$5 -> 6000 | G15: Yes | H15: =IF(G15="Yes",D15*Assumptions!$B$8,0) -> 3000 | I15: =D15+E15+F15+H15 -> 51000 | J15: =D15*Assumptions!$B$6 -> 3600 | K15: =Assumptions!$B$7 -> 200 | L15: =IF(I15*12<=Assumptions!$B$9,I15*Assumptions!$B$10,I15*Assumptions!$B$11) -> 7650 | M15: =J15+K15+L15 -> 11450 | N15: =I15-M15 -> 39550
A16: E012 | B16: Meera Pillai | C16: Marketing | D16: 25000 | E16: =D16*Assumptions!$B$4 -> 10000 | F16: =D16*Assumptions!$B$5 -> 5000 | G16: No | H16: =IF(G16="Yes",D16*Assumptions!$B$8,0) -> 0 | I16: =D16+E16+F16+H16 -> 40000 | J16: =D16*Assumptions!$B$6 -> 3000 | K16: =Assumptions!$B$7 -> 200 | L16: =IF(I16*12<=Assumptions!$B$9,I16*Assumptions!$B$10,I16*Assumptions!$B$11) -> 2000 | M16: =J16+K16+L16 -> 5200 | N16: =I16-M16 -> 34800
C17: TOTAL | D17: =SUM(D5:D16) -> 495000 | E17: =SUM(E5:E16) -> 198000 | F17: =SUM(F5:F16) -> 99000 | H17: =SUM(H5:H16) -> 38000 | I17: =SUM(I5:I16) -> 830000 | J17: =SUM(J5:J16) -> 59400 | K17: =SUM(K5:K16) -> 2400 | L17: =SUM(L5:L16) -> 116500 | M17: =SUM(M5:M16) -> 178300 | N17: =SUM(N5:N16) -> 651700

Sheet Dashboard
A1: Salary Dashboard
A3: Department | B3: Headcount | C3: Total Gross | D3: Total Net Payout | E3: Avg Net Salary
A5: Finance | B5: =COUNTIF('Salary Calculator'!$C$5:$C$16,A5) -> 2 | C5: =SUMIF('Salary Calculator'!$C$5:$C$16,A5,'Salary Calculator'!$I$5:$I$16) -> 161500 | D5: =SUMIF('Salary Calculator'!$C$5:$C$16,A5,'Salary Calculator'!$N$5:$N$16) -> 125475 | E5: =D5/B5 -> 62737.5
A6: HR | B6: =COUNTIF('Salary Calculator'!$C$5:$C$16,A6) -> 2 | C6: =SUMIF('Salary Calculator'!$C$5:$C$16,A6,'Salary Calculator'!$I$5:$I$16) -> 108000 | D6: =SUMIF('Salary Calculator'!$C$5:$C$16,A6,'Salary Calculator'!$N$5:$N$16) -> 87600 | E6: =D6/B6 -> 43800
A7: IT | B7: =COUNTIF('Salary Calculator'!$C$5:$C$16,A7) -> 3 | C7: =SUMIF('Salary Calculator'!$C$5:$C$16,A7,'Salary Calculator'!$I$5:$I$16) -> 161500 | D7: =SUMIF('Salary Calculator'!$C$5:$C$16,A7,'Salary Calculator'!$N$5:$N$16) -> 125275 | E7: =D7/B7 -> 41758.333
A8: Marketing | B8: =COUNTIF('Salary Calculator'!$C$5:$C$16,A8) -> 2 | C8: =SUMIF('Salary Calculator'!$C$5:$C$16,A8,'Salary Calculator'!$I$5:$I$16) -> 91000 | D8: =SUMIF('Salary Calculator'!$C$5:$C$16,A8,'Salary Calculator'!$N$5:$N$16) -> 74350 | E8: =D8/B8 -> 37175
A9: Sales | B9: =COUNTIF('Salary Calculator'!$C$5:$C$16,A9) -> 3 | C9: =SUMIF('Salary Calculator'!$C$5:$C$16,A9,'Salary Calculator'!$I$5:$I$16) -> 308000 | D9: =SUMIF('Salary Calculator'!$C$5:$C$16,A9,'Salary Calculator'!$N$5:$N$16) -> 239000 | E9: =D9/B9 -> 79666.667
A11: Total Monthly Payroll (Net) | B11: ='Salary Calculator'!N17 -> 651700
A12: Total Headcount | B12: 12
