Workbook

Sheet Transactions
A1: Personal Expense Tracker - Transactions
A2: Log every expense here (Date, Category, Description, Amount). Summary and Dashboard sheets update automatically.
A4: Date | B4: Category | C4: Description | D4: Amount | E4: Payment Method
A5: 2026-06-08 | B5: Savings | C5: Transfer to savings | D5: 5030 | E5: Cash
A6: 2026-06-21 | B6: Groceries | C6: Online grocery order | D6: 553 | E6: Cash
A7: 2026-06-09 | B7: Savings | C7: Transfer to savings | D7: 3570 | E7: Cash
A8: 2026-06-18 | B8: Savings | C8: Mutual fund SIP | D8: 5253 | E8: Credit Card
A9: 2026-06-08 | B9: Utilities | C9: Mobile recharge | D9: 362 | E9: UPI
A10: 2026-06-06 | B10: Rent | C10: Monthly rent | D10: 18000 | E10: Debit Card
A11: 2026-06-16 | B11: Healthcare | C11: Gym membership | D11: 1948 | E11: Cash
A12: 2026-06-24 | B12: Shopping | C12: Clothing | D12: 3494 | E12: UPI
A13: 2026-06-02 | B13: Utilities | C13: Mobile recharge | D13: 1188 | E13: Debit Card
A14: 2026-06-22 | B14: Healthcare | C14: Gym membership | D14: 1433 | E14: Cash
A15: 2026-06-17 | B15: Healthcare | C15: Gym membership | D15: 1637 | E15: Cash
A16: 2026-06-19 | B16: Transport | C16: Metro card top-up | D16: 1496 | E16: UPI
... A94: 2026-07-19 | B94: Utilities | C94: Water bill | D94: 1395 | E94: Credit Card

Sheet Budget
A1: Monthly Budget by Category
A2: Yellow cells are editable budget limits per category.
A4: Category | B4: Monthly Budget
A5: Rent | B5: 18000
A6: Groceries | B6: 8000
A7: Utilities | B7: 4000
A8: Transport | B8: 3000
A9: Dining Out | B9: 3000
A10: Entertainment | B10: 2500
A11: Healthcare | B11: 3000
A12: Shopping | B12: 4000
A13: Savings | B13: 10000

Sheet Monthly Summary
A1: Category Report vs Budget
A2: Actual spend pulled live from Transactions; compares against Budget sheet.
A4: Category | B4: Budget | C4: Actual Spend | D4: Remaining | E4: % Used | F4: Status
A5: Rent | B5: =VLOOKUP(A5,Budget!$A$5:$B$13,2,0) -> 18000 | C5: =SUMIF(Transactions!$B$5:$B$94,A5,Transactions!$D$5:$D$94) -> 180000 | D5: =B5-C5 -> -162000 | E5: =C5/B5 -> 10 | F5: =IF(C5>B5,"Over Budget","OK") -> Over Budget
A6: Groceries | B6: =VLOOKUP(A6,Budget!$A$5:$B$13,2,0) -> 8000 | C6: =SUMIF(Transactions!$B$5:$B$94,A6,Transactions!$D$5:$D$94) -> 13868 | D6: =B6-C6 -> -5868 | E6: =C6/B6 -> 1.7335 | F6: =IF(C6>B6,"Over Budget","OK") -> Over Budget
A7: Utilities | B7: =VLOOKUP(A7,Budget!$A$5:$B$13,2,0) -> 4000 | C7: =SUMIF(Transactions!$B$5:$B$94,A7,Transactions!$D$5:$D$94) -> 15213 | D7: =B7-C7 -> -11213 | E7: =C7/B7 -> 3.80325 | F7: =IF(C7>B7,"Over Budget","OK") -> Over Budget
A8: Transport | B8: =VLOOKUP(A8,Budget!$A$5:$B$13,2,0) -> 3000 | C8: =SUMIF(Transactions!$B$5:$B$94,A8,Transactions!$D$5:$D$94) -> 4352 | D8: =B8-C8 -> -1352 | E8: =C8/B8 -> 1.4506667 | F8: =IF(C8>B8,"Over Budget","OK") -> Over Budget
A9: Dining Out | B9: =VLOOKUP(A9,Budget!$A$5:$B$13,2,0) -> 3000 | C9: =SUMIF(Transactions!$B$5:$B$94,A9,Transactions!$D$5:$D$94) -> 8828 | D9: =B9-C9 -> -5828 | E9: =C9/B9 -> 2.9426667 | F9: =IF(C9>B9,"Over Budget","OK") -> Over Budget
A10: Entertainment | B10: =VLOOKUP(A10,Budget!$A$5:$B$13,2,0) -> 2500 | C10: =SUMIF(Transactions!$B$5:$B$94,A10,Transactions!$D$5:$D$94) -> 12155 | D10: =B10-C10 -> -9655 | E10: =C10/B10 -> 4.862 | F10: =IF(C10>B10,"Over Budget","OK") -> Over Budget
A11: Healthcare | B11: =VLOOKUP(A11,Budget!$A$5:$B$13,2,0) -> 3000 | C11: =SUMIF(Transactions!$B$5:$B$94,A11,Transactions!$D$5:$D$94) -> 22440 | D11: =B11-C11 -> -19440 | E11: =C11/B11 -> 7.48 | F11: =IF(C11>B11,"Over Budget","OK") -> Over Budget
A12: Shopping | B12: =VLOOKUP(A12,Budget!$A$5:$B$13,2,0) -> 4000 | C12: =SUMIF(Transactions!$B$5:$B$94,A12,Transactions!$D$5:$D$94) -> 32905 | D12: =B12-C12 -> -28905 | E12: =C12/B12 -> 8.22625 | F12: =IF(C12>B12,"Over Budget","OK") -> Over Budget
A13: Savings | B13: =VLOOKUP(A13,Budget!$A$5:$B$13,2,0) -> 10000 | C13: =SUMIF(Transactions!$B$5:$B$94,A13,Transactions!$D$5:$D$94) -> 81696 | D13: =B13-C13 -> -71696 | E13: =C13/B13 -> 8.1696 | F13: =IF(C13>B13,"Over Budget","OK") -> Over Budget
A14: TOTAL | B14: =SUM(B5:B13) -> 55500 | C14: =SUM(C5:C13) -> 371457 | D14: =SUM(D5:D13) -> -315957

Sheet Dashboard
A1: Expense Dashboard
A3: Month | B3: Total Spend
A5: June 2026 | B5: =SUMPRODUCT((TEXT(Transactions!$A$5:$A$94,"yyyy-mm")="2026-06")*Transactions!$D$5:$D$94) -> 164324
A6: July 2026 | B6: =SUMPRODUCT((TEXT(Transactions!$A$5:$A$94,"yyyy-mm")="2026-07")*Transactions!$D$5:$D$94) -> 207133
A8: Categories Over Budget | B8: =COUNTIF('Monthly Summary'!$F$5:$F$13,"Over Budget") -> 9
A9: Total Spend (All) | B9: ='Monthly Summary'!C14 -> 371457
